{
    "area":  "backend",
    "summary":  "Logged a backend mini update for the upload workflow surface to preserve stronger stability across release notes. This entry keeps the public shipping timeline growing in small, traceable steps.",
    "publishedAt":  "2026-05-13T04:33:17.6228211+00:00",
    "tags":  [
                 "backend",
                 "upload-workflow",
                 "stability"
             ],
    "status":  "shipped",
    "title":  "Upload workflow stability marker",
    "id":  "backend-update-722"
}
