{
    "id":  "backend-update-166",
    "title":  "Public updates route traceability marker",
    "summary":  "Logged a backend mini update for the public updates route surface to preserve a clearer shipping trail. This entry keeps the public shipping timeline growing in small, traceable steps.",
    "area":  "backend",
    "status":  "shipped",
    "publishedAt":  "2026-04-19T06:21:47.441Z",
    "tags":  [
                 "backend",
                 "public-updates-route",
                 "traceability"
             ]
}
